{
  "project_info": {
    "project_number": "920660726894",
    "firebase_url": "https://ciam-9186c-default-rtdb.firebaseio.com",
    "project_id": "ciam-9186c",
    "storage_bucket": "ciam-9186c.appspot.com"
  },
  "client": [
    {
      "client_info": {
        "mobilesdk_app_id": "1:920660726894:android:91cf1ac75f60b062f2827f",
        "android_client_info": {
          "package_name": "com.ciamdoc.doctor"
        }
      },
      "oauth_client": [
        {
          "client_id": "920660726894-8ts21944mnu6kb7b96jfs2bn0viealmr.apps.googleusercontent.com",
          "client_type": 1,
          "android_info": {
            "package_name": "com.ciamdoc.doctor",
            "certificate_hash": "9c67d724755d1deeb89f1a3375d65f6a39ae4d0c"
          }
        },
        {
          "client_id": "920660726894-eidjp2h2jnu1vi7q9nsu60a126n5uot0.apps.googleusercontent.com",
          "client_type": 1,
          "android_info": {
            "package_name": "com.ciamdoc.doctor",
            "certificate_hash": "1e9ed880cbd27d1eb1d4c508e30e5a706703cdce"
          }
        },
        {
          "client_id": "920660726894-ul8tmbr9ntbrjpq96q2b4jpv82d3n2ls.apps.googleusercontent.com",
          "client_type": 1,
          "android_info": {
            "package_name": "com.ciamdoc.doctor",
            "certificate_hash": "39a6b6592ff0218e2282d6e96727942718e46dee"
          }
        },
        {
          "client_id": "920660726894-vcnek5jt86950ot9qkrrn612taspco6b.apps.googleusercontent.com",
          "client_type": 3
        }
      ],
      "api_key": [
        {
          "current_key": "AIzaSyCpZ88gU4PJ-xQfI4-S1I32heUxQyDFC-E"
        }
      ],
      "services": {
        "appinvite_service": {
          "other_platform_oauth_client": [
            {
              "client_id": "920660726894-vcnek5jt86950ot9qkrrn612taspco6b.apps.googleusercontent.com",
              "client_type": 3
            },
            {
              "client_id": "920660726894-4kmiek8ttno4ita5gtfi1kg9l5toaksp.apps.googleusercontent.com",
              "client_type": 2,
              "ios_info": {
                "bundle_id": "com.ciamdoc.doctor"
              }
            }
          ]
        }
      }
    },
    {
      "client_info": {
        "mobilesdk_app_id": "1:920660726894:android:20cc729250f25541f2827f",
        "android_client_info": {
          "package_name": "com.ciamlb.ciam_lab"
        }
      },
      "oauth_client": [
        {
          "client_id": "920660726894-2op0ckljjsd0ar8ilcqu15m7a52pql5m.apps.googleusercontent.com",
          "client_type": 1,
          "android_info": {
            "package_name": "com.ciamlb.ciam_lab",
            "certificate_hash": "9c67d724755d1deeb89f1a3375d65f6a39ae4d0c"
          }
        },
        {
          "client_id": "920660726894-5scarfm256m0ltt2ebspcadbh8g9lg5m.apps.googleusercontent.com",
          "client_type": 1,
          "android_info": {
            "package_name": "com.ciamlb.ciam_lab",
            "certificate_hash": "1e9ed880cbd27d1eb1d4c508e30e5a706703cdce"
          }
        },
        {
          "client_id": "920660726894-pv604i5egfth2if5h7cu456hf53n8a8l.apps.googleusercontent.com",
          "client_type": 1,
          "android_info": {
            "package_name": "com.ciamlb.ciam_lab",
            "certificate_hash": "39a6b6592ff0218e2282d6e96727942718e46dee"
          }
        },
        {
          "client_id": "920660726894-vcnek5jt86950ot9qkrrn612taspco6b.apps.googleusercontent.com",
          "client_type": 3
        }
      ],
      "api_key": [
        {
          "current_key": "AIzaSyCpZ88gU4PJ-xQfI4-S1I32heUxQyDFC-E"
        }
      ],
      "services": {
        "appinvite_service": {
          "other_platform_oauth_client": [
            {
              "client_id": "920660726894-vcnek5jt86950ot9qkrrn612taspco6b.apps.googleusercontent.com",
              "client_type": 3
            },
            {
              "client_id": "920660726894-4kmiek8ttno4ita5gtfi1kg9l5toaksp.apps.googleusercontent.com",
              "client_type": 2,
              "ios_info": {
                "bundle_id": "com.ciamdoc.doctor"
              }
            }
          ]
        }
      }
    },
    {
      "client_info": {
        "mobilesdk_app_id": "1:920660726894:android:ee6af4348d4c0a2df2827f",
        "android_client_info": {
          "package_name": "com.ciampt.patient"
        }
      },
      "oauth_client": [
        {
          "client_id": "920660726894-8vh101rhqd5nelceli00maacibpdt6hq.apps.googleusercontent.com",
          "client_type": 1,
          "android_info": {
            "package_name": "com.ciampt.patient",
            "certificate_hash": "1e9ed880cbd27d1eb1d4c508e30e5a706703cdce"
          }
        },
        {
          "client_id": "920660726894-b5nrgoa6cp9e3ngl0o4lmnqgun88ldlt.apps.googleusercontent.com",
          "client_type": 1,
          "android_info": {
            "package_name": "com.ciampt.patient",
            "certificate_hash": "39a6b6592ff0218e2282d6e96727942718e46dee"
          }
        },
        {
          "client_id": "920660726894-e2e6d31g5n4j0odibn8j4b08p8pt432h.apps.googleusercontent.com",
          "client_type": 1,
          "android_info": {
            "package_name": "com.ciampt.patient",
            "certificate_hash": "9c67d724755d1deeb89f1a3375d65f6a39ae4d0c"
          }
        },
        {
          "client_id": "920660726894-vcnek5jt86950ot9qkrrn612taspco6b.apps.googleusercontent.com",
          "client_type": 3
        }
      ],
      "api_key": [
        {
          "current_key": "AIzaSyCpZ88gU4PJ-xQfI4-S1I32heUxQyDFC-E"
        }
      ],
      "services": {
        "appinvite_service": {
          "other_platform_oauth_client": [
            {
              "client_id": "920660726894-vcnek5jt86950ot9qkrrn612taspco6b.apps.googleusercontent.com",
              "client_type": 3
            },
            {
              "client_id": "920660726894-4kmiek8ttno4ita5gtfi1kg9l5toaksp.apps.googleusercontent.com",
              "client_type": 2,
              "ios_info": {
                "bundle_id": "com.ciamdoc.doctor"
              }
            }
          ]
        }
      }
    },
    {
      "client_info": {
        "mobilesdk_app_id": "1:920660726894:android:62655cc125a42cbcf2827f",
        "android_client_info": {
          "package_name": "com.in.doctor"
        }
      },
      "oauth_client": [
        {
          "client_id": "920660726894-ieue3jfpvkiq298natrmo9kacvovmpg3.apps.googleusercontent.com",
          "client_type": 1,
          "android_info": {
            "package_name": "com.in.doctor",
            "certificate_hash": "1e9ed880cbd27d1eb1d4c508e30e5a706703cdce"
          }
        },
        {
          "client_id": "920660726894-sknvudtg1jjset8tii5d01gnb22qvlp0.apps.googleusercontent.com",
          "client_type": 1,
          "android_info": {
            "package_name": "com.in.doctor",
            "certificate_hash": "39a6b6592ff0218e2282d6e96727942718e46dee"
          }
        },
        {
          "client_id": "920660726894-uak86fgglhh61pqiu57si6qc6uliuji1.apps.googleusercontent.com",
          "client_type": 1,
          "android_info": {
            "package_name": "com.in.doctor",
            "certificate_hash": "9c67d724755d1deeb89f1a3375d65f6a39ae4d0c"
          }
        },
        {
          "client_id": "920660726894-vcnek5jt86950ot9qkrrn612taspco6b.apps.googleusercontent.com",
          "client_type": 3
        }
      ],
      "api_key": [
        {
          "current_key": "AIzaSyCpZ88gU4PJ-xQfI4-S1I32heUxQyDFC-E"
        }
      ],
      "services": {
        "appinvite_service": {
          "other_platform_oauth_client": [
            {
              "client_id": "920660726894-vcnek5jt86950ot9qkrrn612taspco6b.apps.googleusercontent.com",
              "client_type": 3
            },
            {
              "client_id": "920660726894-4kmiek8ttno4ita5gtfi1kg9l5toaksp.apps.googleusercontent.com",
              "client_type": 2,
              "ios_info": {
                "bundle_id": "com.ciamdoc.doctor"
              }
            }
          ]
        }
      }
    },
    {
      "client_info": {
        "mobilesdk_app_id": "1:920660726894:android:bea2bb142453cdadf2827f",
        "android_client_info": {
          "package_name": "com.in.patient"
        }
      },
      "oauth_client": [
        {
          "client_id": "920660726894-0el024vrgqrhbsl7j6h5k3575i0rstjv.apps.googleusercontent.com",
          "client_type": 1,
          "android_info": {
            "package_name": "com.in.patient",
            "certificate_hash": "39a6b6592ff0218e2282d6e96727942718e46dee"
          }
        },
        {
          "client_id": "920660726894-49d153hetlcv2u2p2vo5t7jptrgu1r9c.apps.googleusercontent.com",
          "client_type": 1,
          "android_info": {
            "package_name": "com.in.patient",
            "certificate_hash": "9c67d724755d1deeb89f1a3375d65f6a39ae4d0c"
          }
        },
        {
          "client_id": "920660726894-pk2rhcfudh6dq6q852c2coedfi36jl1g.apps.googleusercontent.com",
          "client_type": 1,
          "android_info": {
            "package_name": "com.in.patient",
            "certificate_hash": "1e9ed880cbd27d1eb1d4c508e30e5a706703cdce"
          }
        },
        {
          "client_id": "920660726894-vcnek5jt86950ot9qkrrn612taspco6b.apps.googleusercontent.com",
          "client_type": 3
        }
      ],
      "api_key": [
        {
          "current_key": "AIzaSyCpZ88gU4PJ-xQfI4-S1I32heUxQyDFC-E"
        }
      ],
      "services": {
        "appinvite_service": {
          "other_platform_oauth_client": [
            {
              "client_id": "920660726894-vcnek5jt86950ot9qkrrn612taspco6b.apps.googleusercontent.com",
              "client_type": 3
            },
            {
              "client_id": "920660726894-4kmiek8ttno4ita5gtfi1kg9l5toaksp.apps.googleusercontent.com",
              "client_type": 2,
              "ios_info": {
                "bundle_id": "com.ciamdoc.doctor"
              }
            }
          ]
        }
      }
    }
  ],
  "configuration_version": "1"
}